LICENSE
README.md
pyproject.toml
setup.py
src/pydplus/__init__.py
src/pydplus/api.py
src/pydplus/auth.py
src/pydplus/core.py
src/pydplus/users.py
src/pydplus.egg-info/PKG-INFO
src/pydplus.egg-info/SOURCES.txt
src/pydplus.egg-info/dependency_links.txt
src/pydplus.egg-info/requires.txt
src/pydplus.egg-info/top_level.txt
src/pydplus/errors/__init__.py
src/pydplus/errors/exceptions.py
src/pydplus/errors/handlers.py
src/pydplus/tests/__init__.py
src/pydplus/tests/resources.py
src/pydplus/tests/test_instantiate_object.py
src/pydplus/utils/__init__.py
src/pydplus/utils/core_utils.py
src/pydplus/utils/helper.py
src/pydplus/utils/log_utils.py
src/pydplus/utils/version.py