Metadata-Version: 2.1
Name: pydplus
Version: 1.0.0b1
Summary: A Python toolset for the RSA ID Plus cloud authentication platform
Home-page: https://github.com/jeffshurtliff/pydplus
Author: Jeff Shurtliff
Author-email: jeff.shurtliff@rsa.com
Project-URL: Issue Tracker, https://github.com/jeffshurtliff/pydplus/issues
Classifier: Development Status :: 4 - Beta
Classifier: Intended Audience :: Information Technology
Classifier: Intended Audience :: System Administrators
Classifier: License :: OSI Approved :: MIT License
Classifier: Natural Language :: English
Classifier: Operating System :: OS Independent
Classifier: Programming Language :: Python :: 3
Classifier: Programming Language :: Python :: 3.9
Classifier: Programming Language :: Python :: 3.10
Classifier: Topic :: Communications :: FIDO
Classifier: Topic :: Office/Business
Classifier: Topic :: Security
Classifier: Topic :: Security :: Cryptography
Classifier: Topic :: Software Development :: Libraries :: Python Modules
Classifier: Topic :: System :: Systems Administration :: Authentication/Directory
Requires-Python: >=3.9.23
Provides-Extra: sphinx
License-File: LICENSE
